{"site": {"site_id": 2326, "region": "MEN", "latitude": -37.957435, "longitude": 145.051922, "intersection_name": "NEPEAN/BAY/KAREN", "detector_count": 24, "first_seen": "2023-01-01", "last_seen": "2026-03-09", "cluster_id": 1, "avg_daily_volume": 101126.0}, "daily_volumes": [{"date": "2025-12-09", "total_volume": 113276, "peak_hour": 16, "peak_hour_volume": 9023}, {"date": "2025-12-10", "total_volume": 115063, "peak_hour": 17, "peak_hour_volume": 9039}, {"date": "2025-12-11", "total_volume": 119084, "peak_hour": 16, "peak_hour_volume": 9199}, {"date": "2025-12-12", "total_volume": 120660, "peak_hour": 16, "peak_hour_volume": 9116}, {"date": "2025-12-13", "total_volume": 102835, "peak_hour": 11, "peak_hour_volume": 8347}, {"date": "2025-12-14", "total_volume": 90231, "peak_hour": 12, "peak_hour_volume": 8314}, {"date": "2025-12-15", "total_volume": 109715, "peak_hour": 16, "peak_hour_volume": 9075}, {"date": "2025-12-16", "total_volume": 116251, "peak_hour": 17, "peak_hour_volume": 9180}, {"date": "2025-12-17", "total_volume": 117852, "peak_hour": 16, "peak_hour_volume": 8849}, {"date": "2025-12-18", "total_volume": 119783, "peak_hour": 16, "peak_hour_volume": 8799}, {"date": "2025-12-19", "total_volume": 118456, "peak_hour": 16, "peak_hour_volume": 8699}, {"date": "2025-12-20", "total_volume": 99675, "peak_hour": 12, "peak_hour_volume": 8306}, {"date": "2025-12-21", "total_volume": 84039, "peak_hour": 12, "peak_hour_volume": 7570}, {"date": "2025-12-22", "total_volume": 109282, "peak_hour": 16, "peak_hour_volume": 8787}, {"date": "2025-12-23", "total_volume": 112755, "peak_hour": 12, "peak_hour_volume": 8699}, {"date": "2025-12-24", "total_volume": 97463, "peak_hour": 12, "peak_hour_volume": 8282}, {"date": "2025-12-25", "total_volume": 56573, "peak_hour": 12, "peak_hour_volume": 6443}, {"date": "2025-12-26", "total_volume": 74568, "peak_hour": 12, "peak_hour_volume": 6677}, {"date": "2025-12-27", "total_volume": 76559, "peak_hour": 12, "peak_hour_volume": 6896}, {"date": "2025-12-28", "total_volume": 74032, "peak_hour": 11, "peak_hour_volume": 6732}, {"date": "2025-12-29", "total_volume": 86742, "peak_hour": 13, "peak_hour_volume": 7466}, {"date": "2025-12-30", "total_volume": 83305, "peak_hour": 12, "peak_hour_volume": 7308}, {"date": "2026-01-01", "total_volume": 59113, "peak_hour": 13, "peak_hour_volume": 4929}, {"date": "2026-01-02", "total_volume": 82460, "peak_hour": 14, "peak_hour_volume": 7145}, {"date": "2026-01-03", "total_volume": 76299, "peak_hour": 11, "peak_hour_volume": 6891}, {"date": "2026-01-04", "total_volume": 69014, "peak_hour": 13, "peak_hour_volume": 6364}, {"date": "2026-01-05", "total_volume": 87950, "peak_hour": 15, "peak_hour_volume": 7365}, {"date": "2026-01-06", "total_volume": 92350, "peak_hour": 16, "peak_hour_volume": 7614}, {"date": "2026-01-07", "total_volume": 87901, "peak_hour": 12, "peak_hour_volume": 6812}, {"date": "2026-01-08", "total_volume": 98073, "peak_hour": 17, "peak_hour_volume": 7940}, {"date": "2026-01-09", "total_volume": 92047, "peak_hour": 12, "peak_hour_volume": 7371}, {"date": "2026-01-10", "total_volume": 87155, "peak_hour": 12, "peak_hour_volume": 7810}, {"date": "2026-01-11", "total_volume": 76819, "peak_hour": 12, "peak_hour_volume": 6916}, {"date": "2026-01-12", "total_volume": 94994, "peak_hour": 17, "peak_hour_volume": 8001}, {"date": "2026-01-13", "total_volume": 99915, "peak_hour": 16, "peak_hour_volume": 8421}, {"date": "2026-01-14", "total_volume": 103233, "peak_hour": 16, "peak_hour_volume": 8575}, {"date": "2026-01-15", "total_volume": 106065, "peak_hour": 17, "peak_hour_volume": 8528}, {"date": "2026-01-16", "total_volume": 107675, "peak_hour": 15, "peak_hour_volume": 8774}, {"date": "2026-01-17", "total_volume": 90887, "peak_hour": 12, "peak_hour_volume": 7958}, {"date": "2026-01-18", "total_volume": 80808, "peak_hour": 12, "peak_hour_volume": 7568}, {"date": "2026-01-19", "total_volume": 100731, "peak_hour": 16, "peak_hour_volume": 8549}, {"date": "2026-01-20", "total_volume": 105856, "peak_hour": 16, "peak_hour_volume": 8678}, {"date": "2026-01-21", "total_volume": 105664, "peak_hour": 16, "peak_hour_volume": 8697}, {"date": "2026-01-22", "total_volume": 110348, "peak_hour": 17, "peak_hour_volume": 8897}, {"date": "2026-01-23", "total_volume": 112277, "peak_hour": 16, "peak_hour_volume": 8987}, {"date": "2026-01-24", "total_volume": 88065, "peak_hour": 12, "peak_hour_volume": 7874}, {"date": "2026-01-25", "total_volume": 77833, "peak_hour": 12, "peak_hour_volume": 7092}, {"date": "2026-01-26", "total_volume": 76335, "peak_hour": 12, "peak_hour_volume": 7279}, {"date": "2026-01-27", "total_volume": 96220, "peak_hour": 16, "peak_hour_volume": 7344}, {"date": "2026-01-28", "total_volume": 108180, "peak_hour": 16, "peak_hour_volume": 8903}, {"date": "2026-01-29", "total_volume": 111347, "peak_hour": 16, "peak_hour_volume": 9197}, {"date": "2026-01-30", "total_volume": 114310, "peak_hour": 16, "peak_hour_volume": 9000}, {"date": "2026-01-31", "total_volume": 97857, "peak_hour": 13, "peak_hour_volume": 8345}, {"date": "2026-02-01", "total_volume": 80947, "peak_hour": 12, "peak_hour_volume": 7705}, {"date": "2026-02-02", "total_volume": 102903, "peak_hour": 17, "peak_hour_volume": 8781}, {"date": "2026-02-03", "total_volume": 106131, "peak_hour": 16, "peak_hour_volume": 9000}, {"date": "2026-02-04", "total_volume": 109291, "peak_hour": 17, "peak_hour_volume": 9519}, {"date": "2026-02-05", "total_volume": 108809, "peak_hour": 17, "peak_hour_volume": 8828}, {"date": "2026-02-06", "total_volume": 108671, "peak_hour": 15, "peak_hour_volume": 8423}, {"date": "2026-02-07", "total_volume": 98144, "peak_hour": 11, "peak_hour_volume": 8506}, {"date": "2026-02-08", "total_volume": 82411, "peak_hour": 12, "peak_hour_volume": 7692}, {"date": "2026-02-09", "total_volume": 96760, "peak_hour": 17, "peak_hour_volume": 8078}, {"date": "2026-02-10", "total_volume": 102673, "peak_hour": 17, "peak_hour_volume": 8507}, {"date": "2026-02-11", "total_volume": 104879, "peak_hour": 15, "peak_hour_volume": 8543}, {"date": "2026-02-12", "total_volume": 108597, "peak_hour": 17, "peak_hour_volume": 8918}, {"date": "2026-02-13", "total_volume": 111734, "peak_hour": 16, "peak_hour_volume": 8664}, {"date": "2026-02-14", "total_volume": 96702, "peak_hour": 12, "peak_hour_volume": 7957}, {"date": "2026-02-15", "total_volume": 82892, "peak_hour": 12, "peak_hour_volume": 7490}, {"date": "2026-02-16", "total_volume": 101239, "peak_hour": 17, "peak_hour_volume": 8470}, {"date": "2026-02-17", "total_volume": 98396, "peak_hour": 17, "peak_hour_volume": 8322}, {"date": "2026-02-18", "total_volume": 108201, "peak_hour": 16, "peak_hour_volume": 9815}, {"date": "2026-02-19", "total_volume": 109171, "peak_hour": 17, "peak_hour_volume": 8919}, {"date": "2026-02-20", "total_volume": 112343, "peak_hour": 15, "peak_hour_volume": 8592}, {"date": "2026-02-21", "total_volume": 104105, "peak_hour": 16, "peak_hour_volume": 8924}, {"date": "2026-02-22", "total_volume": 82875, "peak_hour": 12, "peak_hour_volume": 7873}, {"date": "2026-02-23", "total_volume": 98795, "peak_hour": 16, "peak_hour_volume": 8172}, {"date": "2026-02-24", "total_volume": 95113, "peak_hour": 17, "peak_hour_volume": 8058}, {"date": "2026-02-25", "total_volume": 102863, "peak_hour": 17, "peak_hour_volume": 8233}, {"date": "2026-02-26", "total_volume": 107835, "peak_hour": 17, "peak_hour_volume": 8718}, {"date": "2026-02-27", "total_volume": 109937, "peak_hour": 16, "peak_hour_volume": 8760}, {"date": "2026-02-28", "total_volume": 96336, "peak_hour": 13, "peak_hour_volume": 7970}, {"date": "2026-03-01", "total_volume": 79464, "peak_hour": 12, "peak_hour_volume": 7542}, {"date": "2026-03-02", "total_volume": 96840, "peak_hour": 17, "peak_hour_volume": 7894}, {"date": "2026-03-03", "total_volume": 101868, "peak_hour": 17, "peak_hour_volume": 8260}, {"date": "2026-03-04", "total_volume": 106906, "peak_hour": 17, "peak_hour_volume": 8606}, {"date": "2026-03-05", "total_volume": 110561, "peak_hour": 16, "peak_hour_volume": 8323}, {"date": "2026-03-06", "total_volume": 126110, "peak_hour": 16, "peak_hour_volume": 8174}, {"date": "2026-03-07", "total_volume": 106499, "peak_hour": 12, "peak_hour_volume": 7389}, {"date": "2026-03-08", "total_volume": 97380, "peak_hour": 12, "peak_hour_volume": 6596}, {"date": "2026-03-09", "total_volume": 85614, "peak_hour": 12, "peak_hour_volume": 6934}], "hourly_profile": [0.007008503528563617, 0.004702815817359697, 0.0034825936549321727, 0.0030651130808870175, 0.004457832985737626, 0.01371996626579986, 0.030922481585812477, 0.046235086021184535, 0.0602591399919799, 0.06041369932505285, 0.0640548931382373, 0.07015616451296483, 0.07310637722048584, 0.07231937968605821, 0.07449773234332224, 0.07918083464269896, 0.07990565877425716, 0.07693682080630697, 0.05586307008249305, 0.03685476083466322, 0.02902285666448257, 0.02405094686658315, 0.01781626581993093, 0.01196700635020583]}