{"site": {"site_id": 2911, "region": "MC1", "latitude": -37.809136, "longitude": 144.969196, "intersection_name": "EXHIBITION/LITTLE LONSDALE", "detector_count": 24, "first_seen": "2023-01-01", "last_seen": "2026-03-09", "cluster_id": null, "avg_daily_volume": 1006.0}, "daily_volumes": [{"date": "2025-12-09", "total_volume": 1144, "peak_hour": 17, "peak_hour_volume": 89}, {"date": "2025-12-10", "total_volume": 1367, "peak_hour": 17, "peak_hour_volume": 111}, {"date": "2025-12-11", "total_volume": 1311, "peak_hour": 17, "peak_hour_volume": 135}, {"date": "2025-12-12", "total_volume": 1412, "peak_hour": 15, "peak_hour_volume": 140}, {"date": "2025-12-13", "total_volume": 995, "peak_hour": 20, "peak_hour_volume": 82}, {"date": "2025-12-14", "total_volume": 929, "peak_hour": 21, "peak_hour_volume": 72}, {"date": "2025-12-15", "total_volume": 1620, "peak_hour": 21, "peak_hour_volume": 268}, {"date": "2025-12-16", "total_volume": 1332, "peak_hour": 18, "peak_hour_volume": 94}, {"date": "2025-12-17", "total_volume": 1220, "peak_hour": 17, "peak_hour_volume": 106}, {"date": "2025-12-18", "total_volume": 414, "peak_hour": 10, "peak_hour_volume": 91}, {"date": "2025-12-19", "total_volume": -96, "peak_hour": 0, "peak_hour_volume": -4}, {"date": "2025-12-20", "total_volume": -96, "peak_hour": 0, "peak_hour_volume": -4}, {"date": "2025-12-21", "total_volume": -96, "peak_hour": 0, "peak_hour_volume": -4}, {"date": "2025-12-22", "total_volume": -96, "peak_hour": 0, "peak_hour_volume": -4}, {"date": "2025-12-23", "total_volume": -96, "peak_hour": 0, "peak_hour_volume": -4}, {"date": "2025-12-24", "total_volume": -96, "peak_hour": 0, "peak_hour_volume": -4}, {"date": "2025-12-25", "total_volume": -96, "peak_hour": 0, "peak_hour_volume": -4}, {"date": "2025-12-26", "total_volume": -96, "peak_hour": 0, "peak_hour_volume": -4}, {"date": "2025-12-27", "total_volume": -96, "peak_hour": 0, "peak_hour_volume": -4}, {"date": "2025-12-28", "total_volume": -78, "peak_hour": 16, "peak_hour_volume": 0}, {"date": "2025-12-29", "total_volume": -92, "peak_hour": 13, "peak_hour_volume": -1}, {"date": "2025-12-30", "total_volume": 173, "peak_hour": 19, "peak_hour_volume": 57}, {"date": "2026-01-01", "total_volume": 640, "peak_hour": 17, "peak_hour_volume": 48}, {"date": "2026-01-02", "total_volume": 826, "peak_hour": 16, "peak_hour_volume": 59}, {"date": "2026-01-03", "total_volume": 802, "peak_hour": 15, "peak_hour_volume": 61}, {"date": "2026-01-04", "total_volume": 643, "peak_hour": 17, "peak_hour_volume": 53}, {"date": "2026-01-05", "total_volume": 799, "peak_hour": 16, "peak_hour_volume": 60}, {"date": "2026-01-06", "total_volume": -667, "peak_hour": 11, "peak_hour_volume": 54}, {"date": "2026-01-07", "total_volume": 707, "peak_hour": 18, "peak_hour_volume": 62}, {"date": "2026-01-08", "total_volume": 927, "peak_hour": 15, "peak_hour_volume": 69}, {"date": "2026-01-09", "total_volume": 923, "peak_hour": 12, "peak_hour_volume": 62}, {"date": "2026-01-10", "total_volume": 891, "peak_hour": 18, "peak_hour_volume": 62}, {"date": "2026-01-11", "total_volume": 814, "peak_hour": 16, "peak_hour_volume": 69}, {"date": "2026-01-12", "total_volume": 888, "peak_hour": 17, "peak_hour_volume": 77}, {"date": "2026-01-13", "total_volume": 941, "peak_hour": 17, "peak_hour_volume": 80}, {"date": "2026-01-14", "total_volume": 1100, "peak_hour": 17, "peak_hour_volume": 93}, {"date": "2026-01-15", "total_volume": 1051, "peak_hour": 17, "peak_hour_volume": 89}, {"date": "2026-01-16", "total_volume": 1130, "peak_hour": 16, "peak_hour_volume": 77}, {"date": "2026-01-17", "total_volume": 980, "peak_hour": 18, "peak_hour_volume": 69}, {"date": "2026-01-18", "total_volume": 776, "peak_hour": 17, "peak_hour_volume": 56}, {"date": "2026-01-19", "total_volume": 928, "peak_hour": 17, "peak_hour_volume": 85}, {"date": "2026-01-20", "total_volume": 1161, "peak_hour": 17, "peak_hour_volume": 93}, {"date": "2026-01-21", "total_volume": 1190, "peak_hour": 17, "peak_hour_volume": 106}, {"date": "2026-01-22", "total_volume": 1159, "peak_hour": 17, "peak_hour_volume": 112}, {"date": "2026-01-23", "total_volume": 1218, "peak_hour": 17, "peak_hour_volume": 89}, {"date": "2026-01-24", "total_volume": 969, "peak_hour": 22, "peak_hour_volume": 74}, {"date": "2026-01-25", "total_volume": 889, "peak_hour": 17, "peak_hour_volume": 72}, {"date": "2026-01-26", "total_volume": 853, "peak_hour": 13, "peak_hour_volume": 87}, {"date": "2026-01-27", "total_volume": 1011, "peak_hour": 17, "peak_hour_volume": 77}, {"date": "2026-01-28", "total_volume": 1292, "peak_hour": 17, "peak_hour_volume": 107}, {"date": "2026-01-29", "total_volume": 1160, "peak_hour": 18, "peak_hour_volume": 98}, {"date": "2026-01-30", "total_volume": 1233, "peak_hour": 11, "peak_hour_volume": 88}, {"date": "2026-01-31", "total_volume": 1126, "peak_hour": 19, "peak_hour_volume": 83}, {"date": "2026-02-01", "total_volume": 817, "peak_hour": 12, "peak_hour_volume": 69}, {"date": "2026-02-02", "total_volume": 1051, "peak_hour": 16, "peak_hour_volume": 83}, {"date": "2026-02-03", "total_volume": 1104, "peak_hour": 17, "peak_hour_volume": 92}, {"date": "2026-02-04", "total_volume": 1135, "peak_hour": 17, "peak_hour_volume": 113}, {"date": "2026-02-05", "total_volume": 1150, "peak_hour": 17, "peak_hour_volume": 95}, {"date": "2026-02-06", "total_volume": 1200, "peak_hour": 16, "peak_hour_volume": 94}, {"date": "2026-02-07", "total_volume": 1027, "peak_hour": 19, "peak_hour_volume": 76}, {"date": "2026-02-08", "total_volume": 885, "peak_hour": 17, "peak_hour_volume": 61}, {"date": "2026-02-09", "total_volume": 998, "peak_hour": 17, "peak_hour_volume": 82}, {"date": "2026-02-10", "total_volume": 1090, "peak_hour": 17, "peak_hour_volume": 91}, {"date": "2026-02-11", "total_volume": 1184, "peak_hour": 14, "peak_hour_volume": 89}, {"date": "2026-02-12", "total_volume": 1214, "peak_hour": 16, "peak_hour_volume": 96}, {"date": "2026-02-13", "total_volume": 1208, "peak_hour": 13, "peak_hour_volume": 88}, {"date": "2026-02-14", "total_volume": 1209, "peak_hour": 17, "peak_hour_volume": 86}, {"date": "2026-02-15", "total_volume": 911, "peak_hour": 16, "peak_hour_volume": 70}, {"date": "2026-02-16", "total_volume": 1131, "peak_hour": 11, "peak_hour_volume": 88}, {"date": "2026-02-17", "total_volume": 1172, "peak_hour": 17, "peak_hour_volume": 103}, {"date": "2026-02-18", "total_volume": 1207, "peak_hour": 17, "peak_hour_volume": 102}, {"date": "2026-02-19", "total_volume": 1207, "peak_hour": 17, "peak_hour_volume": 105}, {"date": "2026-02-20", "total_volume": 1248, "peak_hour": 14, "peak_hour_volume": 90}, {"date": "2026-02-21", "total_volume": 1163, "peak_hour": 23, "peak_hour_volume": 87}, {"date": "2026-02-22", "total_volume": 1451, "peak_hour": 12, "peak_hour_volume": 137}, {"date": "2026-02-23", "total_volume": 1048, "peak_hour": 8, "peak_hour_volume": 76}, {"date": "2026-02-24", "total_volume": 1187, "peak_hour": 17, "peak_hour_volume": 89}, {"date": "2026-02-25", "total_volume": 1138, "peak_hour": 17, "peak_hour_volume": 110}, {"date": "2026-02-26", "total_volume": 1359, "peak_hour": 18, "peak_hour_volume": 107}, {"date": "2026-02-27", "total_volume": 1478, "peak_hour": 23, "peak_hour_volume": 145}, {"date": "2026-02-28", "total_volume": 2638, "peak_hour": 19, "peak_hour_volume": 184}, {"date": "2026-03-01", "total_volume": 2413, "peak_hour": 17, "peak_hour_volume": 190}, {"date": "2026-03-02", "total_volume": 1316, "peak_hour": 17, "peak_hour_volume": 97}, {"date": "2026-03-03", "total_volume": 1190, "peak_hour": 17, "peak_hour_volume": 90}, {"date": "2026-03-04", "total_volume": 1147, "peak_hour": 17, "peak_hour_volume": 78}, {"date": "2026-03-05", "total_volume": 1251, "peak_hour": 17, "peak_hour_volume": 100}, {"date": "2026-03-06", "total_volume": 1151, "peak_hour": 21, "peak_hour_volume": 77}, {"date": "2026-03-07", "total_volume": 1057, "peak_hour": 21, "peak_hour_volume": 77}, {"date": "2026-03-08", "total_volume": 885, "peak_hour": 18, "peak_hour_volume": 62}, {"date": "2026-03-09", "total_volume": 879, "peak_hour": 19, "peak_hour_volume": 62}], "hourly_profile": null}