{"site": {"site_id": 3511, "region": "MNP", "latitude": -37.764462, "longitude": 144.923681, "intersection_name": "MT ALEXANDER/KELLAWAY/TAYLORS", "detector_count": 24, "first_seen": "2023-01-01", "last_seen": "2026-03-09", "cluster_id": 0, "avg_daily_volume": 68002.0}, "daily_volumes": [{"date": "2025-12-09", "total_volume": 67923, "peak_hour": 17, "peak_hour_volume": 4758}, {"date": "2025-12-10", "total_volume": 69495, "peak_hour": 17, "peak_hour_volume": 4654}, {"date": "2025-12-11", "total_volume": 70664, "peak_hour": 17, "peak_hour_volume": 4431}, {"date": "2025-12-12", "total_volume": 72479, "peak_hour": 17, "peak_hour_volume": 4688}, {"date": "2025-12-13", "total_volume": 70101, "peak_hour": 11, "peak_hour_volume": 4502}, {"date": "2025-12-14", "total_volume": 64090, "peak_hour": 12, "peak_hour_volume": 4556}, {"date": "2025-12-15", "total_volume": 67966, "peak_hour": 16, "peak_hour_volume": 4693}, {"date": "2025-12-16", "total_volume": 69215, "peak_hour": 17, "peak_hour_volume": 4738}, {"date": "2025-12-17", "total_volume": 69958, "peak_hour": 17, "peak_hour_volume": 4610}, {"date": "2025-12-18", "total_volume": 70320, "peak_hour": 17, "peak_hour_volume": 4454}, {"date": "2025-12-19", "total_volume": 72237, "peak_hour": 12, "peak_hour_volume": 4596}, {"date": "2025-12-20", "total_volume": 68097, "peak_hour": 12, "peak_hour_volume": 4410}, {"date": "2025-12-21", "total_volume": 59554, "peak_hour": 11, "peak_hour_volume": 4106}, {"date": "2025-12-22", "total_volume": 68262, "peak_hour": 15, "peak_hour_volume": 4525}, {"date": "2025-12-23", "total_volume": 70804, "peak_hour": 12, "peak_hour_volume": 4568}, {"date": "2025-12-24", "total_volume": 66299, "peak_hour": 12, "peak_hour_volume": 4623}, {"date": "2025-12-25", "total_volume": 42271, "peak_hour": 12, "peak_hour_volume": 3030}, {"date": "2025-12-26", "total_volume": 47430, "peak_hour": 15, "peak_hour_volume": 2910}, {"date": "2025-12-27", "total_volume": 54971, "peak_hour": 12, "peak_hour_volume": 3725}, {"date": "2025-12-28", "total_volume": 53090, "peak_hour": 12, "peak_hour_volume": 3498}, {"date": "2025-12-29", "total_volume": 57142, "peak_hour": 12, "peak_hour_volume": 3729}, {"date": "2025-12-30", "total_volume": 59013, "peak_hour": 12, "peak_hour_volume": 3979}, {"date": "2026-01-01", "total_volume": 47239, "peak_hour": 14, "peak_hour_volume": 3000}, {"date": "2026-01-02", "total_volume": 57070, "peak_hour": 12, "peak_hour_volume": 3876}, {"date": "2026-01-03", "total_volume": 54071, "peak_hour": 12, "peak_hour_volume": 3720}, {"date": "2026-01-04", "total_volume": 51814, "peak_hour": 15, "peak_hour_volume": 3676}, {"date": "2026-01-05", "total_volume": 61200, "peak_hour": 17, "peak_hour_volume": 4306}, {"date": "2026-01-06", "total_volume": 62889, "peak_hour": 17, "peak_hour_volume": 4314}, {"date": "2026-01-07", "total_volume": 59290, "peak_hour": 17, "peak_hour_volume": 3899}, {"date": "2026-01-08", "total_volume": 63769, "peak_hour": 17, "peak_hour_volume": 4491}, {"date": "2026-01-09", "total_volume": 62370, "peak_hour": 17, "peak_hour_volume": 4000}, {"date": "2026-01-10", "total_volume": 65435, "peak_hour": 12, "peak_hour_volume": 4616}, {"date": "2026-01-11", "total_volume": 59670, "peak_hour": 12, "peak_hour_volume": 4336}, {"date": "2026-01-12", "total_volume": 63932, "peak_hour": 17, "peak_hour_volume": 4653}, {"date": "2026-01-13", "total_volume": 66402, "peak_hour": 17, "peak_hour_volume": 4896}, {"date": "2026-01-14", "total_volume": 67809, "peak_hour": 17, "peak_hour_volume": 4748}, {"date": "2026-01-15", "total_volume": 68333, "peak_hour": 17, "peak_hour_volume": 4775}, {"date": "2026-01-16", "total_volume": 71143, "peak_hour": 16, "peak_hour_volume": 4778}, {"date": "2026-01-17", "total_volume": 67156, "peak_hour": 12, "peak_hour_volume": 4554}, {"date": "2026-01-18", "total_volume": 59373, "peak_hour": 12, "peak_hour_volume": 4075}, {"date": "2026-01-19", "total_volume": 65981, "peak_hour": 17, "peak_hour_volume": 4719}, {"date": "2026-01-20", "total_volume": 68164, "peak_hour": 17, "peak_hour_volume": 4792}, {"date": "2026-01-21", "total_volume": 70476, "peak_hour": 17, "peak_hour_volume": 5008}, {"date": "2026-01-22", "total_volume": 70296, "peak_hour": 17, "peak_hour_volume": 4753}, {"date": "2026-01-23", "total_volume": 72473, "peak_hour": 16, "peak_hour_volume": 4690}, {"date": "2026-01-24", "total_volume": 62233, "peak_hour": 11, "peak_hour_volume": 4383}, {"date": "2026-01-25", "total_volume": 58657, "peak_hour": 13, "peak_hour_volume": 4059}, {"date": "2026-01-26", "total_volume": 55984, "peak_hour": 13, "peak_hour_volume": 3991}, {"date": "2026-01-27", "total_volume": 62964, "peak_hour": 17, "peak_hour_volume": 4499}, {"date": "2026-01-28", "total_volume": 70302, "peak_hour": 17, "peak_hour_volume": 4952}, {"date": "2026-01-29", "total_volume": 70820, "peak_hour": 17, "peak_hour_volume": 4863}, {"date": "2026-01-30", "total_volume": 73400, "peak_hour": 17, "peak_hour_volume": 4877}, {"date": "2026-01-31", "total_volume": 70985, "peak_hour": 11, "peak_hour_volume": 4784}, {"date": "2026-02-01", "total_volume": 64211, "peak_hour": 12, "peak_hour_volume": 4639}, {"date": "2026-02-02", "total_volume": 68178, "peak_hour": 17, "peak_hour_volume": 5021}, {"date": "2026-02-03", "total_volume": 69116, "peak_hour": 17, "peak_hour_volume": 4872}, {"date": "2026-02-04", "total_volume": 70428, "peak_hour": 17, "peak_hour_volume": 5148}, {"date": "2026-02-05", "total_volume": 70686, "peak_hour": 17, "peak_hour_volume": 5023}, {"date": "2026-02-06", "total_volume": 73113, "peak_hour": 17, "peak_hour_volume": 4835}, {"date": "2026-02-07", "total_volume": 71077, "peak_hour": 12, "peak_hour_volume": 4807}, {"date": "2026-02-08", "total_volume": 63090, "peak_hour": 12, "peak_hour_volume": 4639}, {"date": "2026-02-09", "total_volume": 65366, "peak_hour": 17, "peak_hour_volume": 4802}, {"date": "2026-02-10", "total_volume": 69306, "peak_hour": 17, "peak_hour_volume": 4844}, {"date": "2026-02-11", "total_volume": 70240, "peak_hour": 17, "peak_hour_volume": 4737}, {"date": "2026-02-12", "total_volume": 71919, "peak_hour": 17, "peak_hour_volume": 4991}, {"date": "2026-02-13", "total_volume": 74628, "peak_hour": 17, "peak_hour_volume": 4736}, {"date": "2026-02-14", "total_volume": 75244, "peak_hour": 14, "peak_hour_volume": 4959}, {"date": "2026-02-15", "total_volume": 64113, "peak_hour": 13, "peak_hour_volume": 4560}, {"date": "2026-02-16", "total_volume": 67967, "peak_hour": 17, "peak_hour_volume": 4877}, {"date": "2026-02-17", "total_volume": 69217, "peak_hour": 17, "peak_hour_volume": 4931}, {"date": "2026-02-18", "total_volume": 71143, "peak_hour": 17, "peak_hour_volume": 4904}, {"date": "2026-02-19", "total_volume": 70709, "peak_hour": 16, "peak_hour_volume": 4999}, {"date": "2026-02-20", "total_volume": 74566, "peak_hour": 16, "peak_hour_volume": 4773}, {"date": "2026-02-21", "total_volume": 71521, "peak_hour": 11, "peak_hour_volume": 4688}, {"date": "2026-02-22", "total_volume": 63081, "peak_hour": 16, "peak_hour_volume": 4635}, {"date": "2026-02-23", "total_volume": 67853, "peak_hour": 17, "peak_hour_volume": 4806}, {"date": "2026-02-24", "total_volume": 68777, "peak_hour": 17, "peak_hour_volume": 4842}, {"date": "2026-02-25", "total_volume": 70643, "peak_hour": 16, "peak_hour_volume": 4834}, {"date": "2026-02-26", "total_volume": 70141, "peak_hour": 17, "peak_hour_volume": 4699}, {"date": "2026-02-27", "total_volume": 73773, "peak_hour": 17, "peak_hour_volume": 4796}, {"date": "2026-02-28", "total_volume": 72975, "peak_hour": 11, "peak_hour_volume": 4836}, {"date": "2026-03-01", "total_volume": 64922, "peak_hour": 12, "peak_hour_volume": 4696}, {"date": "2026-03-02", "total_volume": 66721, "peak_hour": 17, "peak_hour_volume": 4786}, {"date": "2026-03-03", "total_volume": 68532, "peak_hour": 17, "peak_hour_volume": 4879}, {"date": "2026-03-04", "total_volume": 69542, "peak_hour": 17, "peak_hour_volume": 4866}, {"date": "2026-03-05", "total_volume": 70524, "peak_hour": 17, "peak_hour_volume": 4995}, {"date": "2026-03-06", "total_volume": 72247, "peak_hour": 17, "peak_hour_volume": 4717}, {"date": "2026-03-07", "total_volume": 66315, "peak_hour": 12, "peak_hour_volume": 4707}, {"date": "2026-03-08", "total_volume": 59038, "peak_hour": 12, "peak_hour_volume": 4014}, {"date": "2026-03-09", "total_volume": 57567, "peak_hour": 12, "peak_hour_volume": 4075}], "hourly_profile": [0.01655528994062209, 0.012558128982279235, 0.010442868614080433, 0.010568116815399422, 0.013762514697035667, 0.023723950491475552, 0.03531870690690665, 0.04081841353803234, 0.047491706943195246, 0.05122783729677537, 0.05451450835969924, 0.05813026196223872, 0.060256835470043346, 0.05974017736653726, 0.060131426535593335, 0.06337680154793425, 0.06485628819846041, 0.06647782584453979, 0.060187782044143386, 0.04989213261398251, 0.043583443770388766, 0.03968586316875106, 0.03323227958959392, 0.0234668393022921]}