{"site": {"site_id": 3671, "region": "CA1", "latitude": -37.776519, "longitude": 144.98974, "intersection_name": "ST GEORGES/MERRI/CHARLES", "detector_count": 24, "first_seen": "2023-01-01", "last_seen": "2026-03-09", "cluster_id": 0, "avg_daily_volume": 89103.0}, "daily_volumes": [{"date": "2025-12-09", "total_volume": 93055, "peak_hour": 17, "peak_hour_volume": 5940}, {"date": "2025-12-10", "total_volume": 97030, "peak_hour": 7, "peak_hour_volume": 6141}, {"date": "2025-12-11", "total_volume": 97265, "peak_hour": 17, "peak_hour_volume": 5776}, {"date": "2025-12-12", "total_volume": 102808, "peak_hour": 17, "peak_hour_volume": 5939}, {"date": "2025-12-13", "total_volume": 98903, "peak_hour": 11, "peak_hour_volume": 6125}, {"date": "2025-12-14", "total_volume": 85644, "peak_hour": 12, "peak_hour_volume": 5723}, {"date": "2025-12-15", "total_volume": 89006, "peak_hour": 17, "peak_hour_volume": 5916}, {"date": "2025-12-16", "total_volume": 93620, "peak_hour": 17, "peak_hour_volume": 6160}, {"date": "2025-12-17", "total_volume": 94914, "peak_hour": 17, "peak_hour_volume": 6171}, {"date": "2025-12-18", "total_volume": 96994, "peak_hour": 17, "peak_hour_volume": 5727}, {"date": "2025-12-19", "total_volume": 100935, "peak_hour": 12, "peak_hour_volume": 5901}, {"date": "2025-12-20", "total_volume": 94274, "peak_hour": 13, "peak_hour_volume": 5815}, {"date": "2025-12-21", "total_volume": 80164, "peak_hour": 12, "peak_hour_volume": 5487}, {"date": "2025-12-22", "total_volume": 86656, "peak_hour": 17, "peak_hour_volume": 5826}, {"date": "2025-12-23", "total_volume": 87548, "peak_hour": 11, "peak_hour_volume": 5495}, {"date": "2025-12-24", "total_volume": 81417, "peak_hour": 12, "peak_hour_volume": 5400}, {"date": "2025-12-25", "total_volume": 60354, "peak_hour": 12, "peak_hour_volume": 4699}, {"date": "2025-12-26", "total_volume": 60781, "peak_hour": 12, "peak_hour_volume": 4214}, {"date": "2025-12-27", "total_volume": 71621, "peak_hour": 11, "peak_hour_volume": 4711}, {"date": "2025-12-28", "total_volume": 71601, "peak_hour": 12, "peak_hour_volume": 4658}, {"date": "2025-12-29", "total_volume": 73981, "peak_hour": 12, "peak_hour_volume": 5001}, {"date": "2025-12-30", "total_volume": 72500, "peak_hour": 14, "peak_hour_volume": 4813}, {"date": "2026-01-01", "total_volume": 64745, "peak_hour": 15, "peak_hour_volume": 3935}, {"date": "2026-01-02", "total_volume": 73441, "peak_hour": 13, "peak_hour_volume": 4985}, {"date": "2026-01-03", "total_volume": 70549, "peak_hour": 11, "peak_hour_volume": 4791}, {"date": "2026-01-04", "total_volume": 70900, "peak_hour": 11, "peak_hour_volume": 4886}, {"date": "2026-01-05", "total_volume": 75289, "peak_hour": 14, "peak_hour_volume": 5102}, {"date": "2026-01-06", "total_volume": 79208, "peak_hour": 17, "peak_hour_volume": 5363}, {"date": "2026-01-07", "total_volume": 74711, "peak_hour": 17, "peak_hour_volume": 4970}, {"date": "2026-01-08", "total_volume": 81599, "peak_hour": 17, "peak_hour_volume": 5455}, {"date": "2026-01-09", "total_volume": 79829, "peak_hour": 17, "peak_hour_volume": 5016}, {"date": "2026-01-10", "total_volume": 84873, "peak_hour": 11, "peak_hour_volume": 5584}, {"date": "2026-01-11", "total_volume": 76181, "peak_hour": 13, "peak_hour_volume": 5086}, {"date": "2026-01-12", "total_volume": 83451, "peak_hour": 17, "peak_hour_volume": 5915}, {"date": "2026-01-13", "total_volume": 88343, "peak_hour": 17, "peak_hour_volume": 6112}, {"date": "2026-01-14", "total_volume": 89996, "peak_hour": 8, "peak_hour_volume": 5802}, {"date": "2026-01-15", "total_volume": 90611, "peak_hour": 17, "peak_hour_volume": 5805}, {"date": "2026-01-16", "total_volume": 95630, "peak_hour": 17, "peak_hour_volume": 5923}, {"date": "2026-01-17", "total_volume": 89808, "peak_hour": 11, "peak_hour_volume": 5752}, {"date": "2026-01-18", "total_volume": 81773, "peak_hour": 12, "peak_hour_volume": 5281}, {"date": "2026-01-19", "total_volume": 87656, "peak_hour": 17, "peak_hour_volume": 5790}, {"date": "2026-01-20", "total_volume": 89973, "peak_hour": 8, "peak_hour_volume": 5969}, {"date": "2026-01-21", "total_volume": 94570, "peak_hour": 17, "peak_hour_volume": 5961}, {"date": "2026-01-22", "total_volume": 95741, "peak_hour": 17, "peak_hour_volume": 6204}, {"date": "2026-01-23", "total_volume": 97193, "peak_hour": 16, "peak_hour_volume": 5940}, {"date": "2026-01-24", "total_volume": 84962, "peak_hour": 10, "peak_hour_volume": 5530}, {"date": "2026-01-25", "total_volume": 80699, "peak_hour": 12, "peak_hour_volume": 5289}, {"date": "2026-01-26", "total_volume": 70875, "peak_hour": 14, "peak_hour_volume": 4718}, {"date": "2026-01-27", "total_volume": 81564, "peak_hour": 8, "peak_hour_volume": 5619}, {"date": "2026-01-28", "total_volume": 92489, "peak_hour": 7, "peak_hour_volume": 6123}, {"date": "2026-01-29", "total_volume": 93030, "peak_hour": 17, "peak_hour_volume": 5967}, {"date": "2026-01-30", "total_volume": 96539, "peak_hour": 17, "peak_hour_volume": 5858}, {"date": "2026-01-31", "total_volume": 91526, "peak_hour": 13, "peak_hour_volume": 5717}, {"date": "2026-02-01", "total_volume": 80242, "peak_hour": 15, "peak_hour_volume": 5450}, {"date": "2026-02-02", "total_volume": 87530, "peak_hour": 17, "peak_hour_volume": 5842}, {"date": "2026-02-03", "total_volume": 88514, "peak_hour": 7, "peak_hour_volume": 5858}, {"date": "2026-02-04", "total_volume": 91833, "peak_hour": 17, "peak_hour_volume": 5828}, {"date": "2026-02-05", "total_volume": 93604, "peak_hour": 18, "peak_hour_volume": 5809}, {"date": "2026-02-06", "total_volume": 95776, "peak_hour": 17, "peak_hour_volume": 5885}, {"date": "2026-02-07", "total_volume": 90824, "peak_hour": 14, "peak_hour_volume": 5812}, {"date": "2026-02-08", "total_volume": 79392, "peak_hour": 12, "peak_hour_volume": 5553}, {"date": "2026-02-09", "total_volume": 84185, "peak_hour": 7, "peak_hour_volume": 5684}, {"date": "2026-02-10", "total_volume": 87277, "peak_hour": 7, "peak_hour_volume": 5698}, {"date": "2026-02-11", "total_volume": 86467, "peak_hour": 16, "peak_hour_volume": 5878}, {"date": "2026-02-12", "total_volume": 95464, "peak_hour": 17, "peak_hour_volume": 5980}, {"date": "2026-02-13", "total_volume": 98966, "peak_hour": 16, "peak_hour_volume": 5936}, {"date": "2026-02-14", "total_volume": 98779, "peak_hour": 17, "peak_hour_volume": 5974}, {"date": "2026-02-15", "total_volume": 87638, "peak_hour": 13, "peak_hour_volume": 5744}, {"date": "2026-02-16", "total_volume": 89571, "peak_hour": 17, "peak_hour_volume": 6001}, {"date": "2026-02-17", "total_volume": 90376, "peak_hour": 7, "peak_hour_volume": 6069}, {"date": "2026-02-18", "total_volume": 94461, "peak_hour": 17, "peak_hour_volume": 6015}, {"date": "2026-02-19", "total_volume": 96369, "peak_hour": 17, "peak_hour_volume": 6195}, {"date": "2026-02-20", "total_volume": 98613, "peak_hour": 17, "peak_hour_volume": 5934}, {"date": "2026-02-21", "total_volume": 97427, "peak_hour": 14, "peak_hour_volume": 5969}, {"date": "2026-02-22", "total_volume": 83097, "peak_hour": 12, "peak_hour_volume": 5574}, {"date": "2026-02-23", "total_volume": 88706, "peak_hour": 17, "peak_hour_volume": 6223}, {"date": "2026-02-24", "total_volume": 89454, "peak_hour": 7, "peak_hour_volume": 6077}, {"date": "2026-02-25", "total_volume": 94006, "peak_hour": 17, "peak_hour_volume": 6210}, {"date": "2026-02-26", "total_volume": 95462, "peak_hour": 17, "peak_hour_volume": 6082}, {"date": "2026-02-27", "total_volume": 98528, "peak_hour": 17, "peak_hour_volume": 5905}, {"date": "2026-02-28", "total_volume": 96734, "peak_hour": 17, "peak_hour_volume": 5874}, {"date": "2026-03-01", "total_volume": 84049, "peak_hour": 12, "peak_hour_volume": 5704}, {"date": "2026-03-02", "total_volume": 88289, "peak_hour": 8, "peak_hour_volume": 5823}, {"date": "2026-03-03", "total_volume": 94131, "peak_hour": 17, "peak_hour_volume": 6216}, {"date": "2026-03-04", "total_volume": 95838, "peak_hour": 17, "peak_hour_volume": 6129}, {"date": "2026-03-05", "total_volume": 97292, "peak_hour": 17, "peak_hour_volume": 6167}, {"date": "2026-03-06", "total_volume": 96719, "peak_hour": 17, "peak_hour_volume": 5895}, {"date": "2026-03-07", "total_volume": 87413, "peak_hour": 11, "peak_hour_volume": 5542}, {"date": "2026-03-08", "total_volume": 78716, "peak_hour": 17, "peak_hour_volume": 5107}, {"date": "2026-03-09", "total_volume": 71464, "peak_hour": 15, "peak_hour_volume": 5011}], "hourly_profile": [0.016597976789387722, 0.011514482990085492, 0.008431877052362955, 0.007407169262120184, 0.008775386772279159, 0.019783664994528008, 0.04120778213198823, 0.050669337152256085, 0.054402067766102576, 0.054748189764435684, 0.0547067455270798, 0.056338685751574906, 0.05836984473458497, 0.05840298251360395, 0.05982881690614933, 0.059811186472788776, 0.06229036588001995, 0.06432018448047153, 0.060149403149171096, 0.04883443170020013, 0.04204455263342809, 0.040637874949273366, 0.03542862000101634, 0.025298370625091614]}