{"site_id": 3556, "model_id": "daily_global_20260311_030552", "forecasts": [{"forecast_date": "2026-03-10", "horizon_days": 1, "predicted_volume": 83760.8984375, "prediction_lower": 61342.30078125, "prediction_upper": 106179.6015625, "actual_volume": null}, {"forecast_date": "2026-03-16", "horizon_days": 7, "predicted_volume": 82720.8984375, "prediction_lower": 61847.0, "prediction_upper": 103594.8984375, "actual_volume": null}, {"forecast_date": "2026-03-23", "horizon_days": 14, "predicted_volume": 82024.8984375, "prediction_lower": 67074.0, "prediction_upper": 96975.796875, "actual_volume": null}, {"forecast_date": "2026-04-06", "horizon_days": 28, "predicted_volume": 56550.3984375, "prediction_lower": 29424.400390625, "prediction_upper": 83676.5, "actual_volume": null}]}