{"site_id": 5256, "model_id": "daily_global_20260311_030552", "forecasts": [{"forecast_date": "2026-03-10", "horizon_days": 1, "predicted_volume": 61653.30078125, "prediction_lower": 43616.80078125, "prediction_upper": 79689.703125, "actual_volume": null}, {"forecast_date": "2026-03-16", "horizon_days": 7, "predicted_volume": 60202.8984375, "prediction_lower": 44792.5, "prediction_upper": 75613.3984375, "actual_volume": null}, {"forecast_date": "2026-03-23", "horizon_days": 14, "predicted_volume": 59770.8984375, "prediction_lower": 50247.3984375, "prediction_upper": 69294.3984375, "actual_volume": null}, {"forecast_date": "2026-04-06", "horizon_days": 28, "predicted_volume": 42886.80078125, "prediction_lower": 25887.5, "prediction_upper": 59886.0, "actual_volume": null}]}